reflex_webcam/__init__.py
reflex_webcam/webcam.py
reflex_webcam-0.0.6.dist-info/LICENSE
reflex_webcam-0.0.6.dist-info/METADATA
reflex_webcam-0.0.6.dist-info/WHEEL
reflex_webcam-0.0.6.dist-info/top_level.txt
reflex_webcam-0.0.6.dist-info/RECORD
